structured_outputs/__init__.py
structured_outputs-0.0.1.dist-info/LICENSE
structured_outputs-0.0.1.dist-info/METADATA
structured_outputs-0.0.1.dist-info/WHEEL
structured_outputs-0.0.1.dist-info/RECORD
